plagiarismdeny/__init__.py
plagiarismdeny-0.1.8.dist-info/METADATA
plagiarismdeny-0.1.8.dist-info/WHEEL
plagiarismdeny-0.1.8.dist-info/top_level.txt
plagiarismdeny-0.1.8.dist-info/RECORD
